__init__.py
docx_report.py
docx_report-0.1.3.dist-info/METADATA
docx_report-0.1.3.dist-info/WHEEL
docx_report-0.1.3.dist-info/RECORD
