Metadata-Version: 2.1
Name: docx-report
Version: 0.1.3
Summary: A wrapper for the python-docx library that simplifies creating Word documents in Python
Author: Chris Hacker
Author-email: 49451910+christopher-hacker@users.noreply.github.com
Requires-Python: >=3.10,<3.13
Classifier: Programming Language :: Python :: 3
Classifier: Programming Language :: Python :: 3.10
Classifier: Programming Language :: Python :: 3.11
Requires-Dist: matplotlib (>=3.8.0,<4.0.0)
Requires-Dist: pandas (>=2.1.1,<3.0.0)
Requires-Dist: pydata-sphinx-theme (>=0.14.1,<0.15.0)
Requires-Dist: pyjanitor (>=0.26.0,<0.27.0)
Requires-Dist: python-docx (>=1.0.1,<2.0.0)
Requires-Dist: pytz (>=2023.3.post1,<2024.0)
Requires-Dist: recommonmark (>=0.7.1,<0.8.0)
Requires-Dist: sphinx-autodoc-typehints (>=1.24.0,<2.0.0)
Requires-Dist: sphinx-click (>=5.0.1,<6.0.0)
